{
    "Ar36": {
        "error": 0.0002480423821802996, 
        "filter_outliers_dict": {
            "filter_outliers": true, 
            "iterations": 1, 
            "std_devs": 2
        }, 
        "fit": "Parabolic", 
        "value": 0.009193005280703957
    }, 
    "Ar37": {
        "error": 0.005226902198558622, 
        "filter_outliers_dict": {
            "filter_outliers": true, 
            "iterations": 1, 
            "std_devs": 2
        }, 
        "fit": "linear", 
        "value": 0.05577603021102586
    }, 
    "Ar38": {
        "error": 0.0025002482611863035, 
        "filter_outliers_dict": {
            "filter_outliers": true, 
            "iterations": 1, 
            "std_devs": 2
        }, 
        "fit": "linear", 
        "value": 0.08620200620301616
    }, 
    "Ar39": {
        "error": 0.009864855281451803, 
        "filter_outliers_dict": {
            "filter_outliers": true, 
            "iterations": 1, 
            "std_devs": 2
        }, 
        "fit": "Parabolic", 
        "value": 8.847510593921825
    }, 
    "Ar40": {
        "error": 0.052321783340233054, 
        "filter_outliers_dict": {
            "filter_outliers": true, 
            "iterations": 1, 
            "std_devs": 2
        }, 
        "fit": "Parabolic", 
        "value": 1601.4659606957455
    }, 
    "Ar41": {
        "error": 0.0037800192961314418, 
        "filter_outliers_dict": {
            "filter_outliers": true, 
            "iterations": 1, 
            "std_devs": 2
        }, 
        "fit": "linear", 
        "value": -0.006159887024474193
    }
}