{
    "Ar36": {
        "error": 0.00026480679168469694, 
        "filter_outliers_dict": {
            "filter_outliers": true, 
            "iterations": 1, 
            "std_devs": 2
        }, 
        "fit": "Parabolic", 
        "value": 0.011518757038466956
    }, 
    "Ar37": {
        "error": 0.004704656060714851, 
        "filter_outliers_dict": {
            "filter_outliers": true, 
            "iterations": 1, 
            "std_devs": 2
        }, 
        "fit": "linear", 
        "value": 0.06381060902676969
    }, 
    "Ar38": {
        "error": 0.002253460308996798, 
        "filter_outliers_dict": {
            "filter_outliers": true, 
            "iterations": 1, 
            "std_devs": 2
        }, 
        "fit": "linear", 
        "value": 0.17432048623110774
    }, 
    "Ar39": {
        "error": 0.010047721776988289, 
        "filter_outliers_dict": {
            "filter_outliers": true, 
            "iterations": 1, 
            "std_devs": 2
        }, 
        "fit": "Parabolic", 
        "value": 15.486105694383081
    }, 
    "Ar40": {
        "error": 0.0808590556357189, 
        "filter_outliers_dict": {
            "filter_outliers": true, 
            "iterations": 1, 
            "std_devs": 2
        }, 
        "fit": "Parabolic", 
        "value": 2908.706652437025
    }, 
    "Ar41": {
        "error": 0.003706621963933236, 
        "filter_outliers_dict": {
            "filter_outliers": true, 
            "iterations": 1, 
            "std_devs": 2
        }, 
        "fit": "linear", 
        "value": 0.059209081567222266
    }
}