{
    "AX": {
        "error": 0.004218481648293289, 
        "filter_outliers_dict": {
            "filter_outliers": true, 
            "iterations": 1, 
            "std_devs": 2
        }, 
        "fit": "average", 
        "value": 0.15106485952427942
    }, 
    "CDD": {
        "error": 3.392130080652264e-06, 
        "filter_outliers_dict": {
            "filter_outliers": true, 
            "iterations": 1, 
            "std_devs": 10
        }, 
        "fit": "average", 
        "value": 9.889673660670533e-06
    }, 
    "H1": {
        "error": 0.0031681213929895566, 
        "filter_outliers_dict": {
            "filter_outliers": true, 
            "iterations": 1, 
            "std_devs": 2
        }, 
        "fit": "average", 
        "value": 0.07224030615576377
    }, 
    "H2": {
        "error": 0.003169185578555652, 
        "filter_outliers_dict": {
            "filter_outliers": true, 
            "iterations": 1, 
            "std_devs": 2
        }, 
        "fit": "average", 
        "value": -0.08556540173832249
    }, 
    "L1": {
        "error": 0.001724660166687509, 
        "filter_outliers_dict": {
            "filter_outliers": true, 
            "iterations": 1, 
            "std_devs": 2
        }, 
        "fit": "average", 
        "value": -0.025952081858427182
    }, 
    "L2": {
        "error": 0.0036017949038093713, 
        "filter_outliers_dict": {
            "filter_outliers": true, 
            "iterations": 1, 
            "std_devs": 2
        }, 
        "fit": "average", 
        "value": -0.009460699075811218
    }
}