{
    "AX": {
        "error": 0.004651346402164627,
        "filter_outliers_dict": {
            "filter_outliers": true,
            "iterations": 1,
            "std_devs": 2
        },
        "fit": "Average",
        "fn": 116,
        "include_baseline_error": false,
        "n": 120,
        "reviewed": true,
        "value": 0.12740835627733632
    },
    "CDD": {
        "error": 1.8859363332899256e-05,
        "filter_outliers_dict": {
            "filter_outliers": true,
            "iterations": 1,
            "std_devs": 10
        },
        "fit": "Average",
        "fn": 120,
        "include_baseline_error": false,
        "n": 120,
        "value": 0.00023735216964269057
    },
    "H1": {
        "error": 0.004362722083680527,
        "filter_outliers_dict": {
            "filter_outliers": true,
            "iterations": 1,
            "std_devs": 2
        },
        "fit": "Average",
        "fn": 119,
        "include_baseline_error": false,
        "n": 120,
        "reviewed": true,
        "value": 0.1303322030340924
    },
    "H2": {
        "error": 0.002490358094320645,
        "filter_outliers_dict": {
            "filter_outliers": true,
            "iterations": 1,
            "std_devs": 2
        },
        "fit": "Average",
        "fn": 116,
        "include_baseline_error": false,
        "n": 120,
        "value": -0.1012310186593697
    },
    "L1": {
        "error": 0.0019308644916053476,
        "filter_outliers_dict": {
            "filter_outliers": true,
            "iterations": 1,
            "std_devs": 2
        },
        "fit": "Average",
        "fn": 115,
        "include_baseline_error": false,
        "n": 120,
        "reviewed": true,
        "value": -0.03204604792416554
    },
    "L2": {
        "error": 0.004249805896330731,
        "filter_outliers_dict": {
            "filter_outliers": true,
            "iterations": 1,
            "std_devs": 2
        },
        "fit": "Average",
        "fn": 116,
        "include_baseline_error": false,
        "n": 120,
        "value": -0.0007041205354998337
    }
}